{
  "physics": {
    "quantum": { 
      "default": true,
      "description": "switch on for fuzzy dark matter."
    },
    "gravity": { 
      "default": true,
      "description": "switch on for self-gravity."
    },
    "hydro": { 
      "default": false,
      "description": "switch on for hydrodynamics (isothermal)."
    },
    "particles": { 
      "default": false,
      "description": "switch on for particle-mesh particles."
    },
    "cosmology": { 
      "default": false,
      "description": "switch on for cosmological factors/comoving units."
    },
    "external_potential": { 
      "default": false,
      "description": "switch on for external gravitational potential."
    }
  },
  "domain": {
    "box_size": { 
      "default": 10.0,
      "description": "periodic domain box size (kpc)."
    },
    "resolution_base": { 
      "default": 32,
      "description": "base resolution per linear dimension."
    },
    "resolution_multiplier": { 
      "default": 1,
      "description": "resolution multiplier."
    }
  },
  "time": {
    "start": 0.0,
    "end": 1.0,
    "adaptive": false
  },
  "output": {
    "path": "./checkpoints",
    "num_checkpoints": 100,
    "save": true,
    "plot_dynamic_range": 100.0
  },
  "quantum": {
    "m_22": { 
      "default": 1.0,
      "description": "axion mass in units of 10^{-22} eV."
    }
  },
  "hydro": {
    "sound_speed": { 
      "default": 1.0,
      "description": "Isothermal sound speed (km/s)."
    }
  },
  "particles": {
    "num_particles": 0,
    "particle_mass": 1.0
  },
  "cosmology": {
    "Omega_m": 0.3,
    "Omega_Lambda": 0.7
  },
  "version": {
    "default": "unknown",
    "description": "version of the jaxion library used to create these parameters (automatically detected)."
  }
}